[
 {
  "default_value": null, 
  "doc_type": "Quotation", 
  "docstatus": 0, 
  "doctype": "Property Setter", 
  "doctype_or_field": "DocField", 
  "field_name": "base_rounded_total", 
  "modified": "2015-06-09 14:34:19.306747", 
  "name": "Quotation-base_rounded_total-hidden", 
  "property": "hidden", 
  "property_type": "Check", 
  "value": "0"
 }, 
 {
  "default_value": null, 
  "doc_type": "Quotation", 
  "docstatus": 0, 
  "doctype": "Property Setter", 
  "doctype_or_field": "DocField", 
  "field_name": "base_rounded_total", 
  "modified": "2015-06-09 14:34:19.379430", 
  "name": "Quotation-base_rounded_total-print_hide", 
  "property": "print_hide", 
  "property_type": "Check", 
  "value": "1"
 }, 
 {
  "default_value": null, 
  "doc_type": "Quotation", 
  "docstatus": 0, 
  "doctype": "Property Setter", 
  "doctype_or_field": "DocField", 
  "field_name": "rounded_total", 
  "modified": "2015-06-09 14:34:19.445636", 
  "name": "Quotation-rounded_total-hidden", 
  "property": "hidden", 
  "property_type": "Check", 
  "value": "0"
 }, 
 {
  "default_value": null, 
  "doc_type": "Quotation", 
  "docstatus": 0, 
  "doctype": "Property Setter", 
  "doctype_or_field": "DocField", 
  "field_name": "rounded_total", 
  "modified": "2015-06-09 14:34:19.519036", 
  "name": "Quotation-rounded_total-print_hide", 
  "property": "print_hide", 
  "property_type": "Check", 
  "value": "0"
 }, 
 {
  "default_value": null, 
  "doc_type": "Sales Order", 
  "docstatus": 0, 
  "doctype": "Property Setter", 
  "doctype_or_field": "DocField", 
  "field_name": "base_rounded_total", 
  "modified": "2015-06-09 14:34:19.592001", 
  "name": "Sales Order-base_rounded_total-hidden", 
  "property": "hidden", 
  "property_type": "Check", 
  "value": "0"
 }, 
 {
  "default_value": null, 
  "doc_type": "Sales Order", 
  "docstatus": 0, 
  "doctype": "Property Setter", 
  "doctype_or_field": "DocField", 
  "field_name": "base_rounded_total", 
  "modified": "2015-06-09 14:34:19.678806", 
  "name": "Sales Order-base_rounded_total-print_hide", 
  "property": "print_hide", 
  "property_type": "Check", 
  "value": "1"
 }, 
 {
  "default_value": null, 
  "doc_type": "Sales Order", 
  "docstatus": 0, 
  "doctype": "Property Setter", 
  "doctype_or_field": "DocField", 
  "field_name": "rounded_total", 
  "modified": "2015-06-09 14:34:19.768884", 
  "name": "Sales Order-rounded_total-hidden", 
  "property": "hidden", 
  "property_type": "Check", 
  "value": "0"
 }, 
 {
  "default_value": null, 
  "doc_type": "Sales Order", 
  "docstatus": 0, 
  "doctype": "Property Setter", 
  "doctype_or_field": "DocField", 
  "field_name": "rounded_total", 
  "modified": "2015-06-09 14:34:19.849293", 
  "name": "Sales Order-rounded_total-print_hide", 
  "property": "print_hide", 
  "property_type": "Check", 
  "value": "0"
 }, 
 {
  "default_value": null, 
  "doc_type": "Sales Invoice", 
  "docstatus": 0, 
  "doctype": "Property Setter", 
  "doctype_or_field": "DocField", 
  "field_name": "base_rounded_total", 
  "modified": "2015-06-09 14:34:19.946679", 
  "name": "Sales Invoice-base_rounded_total-hidden", 
  "property": "hidden", 
  "property_type": "Check", 
  "value": "0"
 }, 
 {
  "default_value": null, 
  "doc_type": "Sales Invoice", 
  "docstatus": 0, 
  "doctype": "Property Setter", 
  "doctype_or_field": "DocField", 
  "field_name": "base_rounded_total", 
  "modified": "2015-06-09 14:34:20.049069", 
  "name": "Sales Invoice-base_rounded_total-print_hide", 
  "property": "print_hide", 
  "property_type": "Check", 
  "value": "1"
 }, 
 {
  "default_value": null, 
  "doc_type": "Sales Invoice", 
  "docstatus": 0, 
  "doctype": "Property Setter", 
  "doctype_or_field": "DocField", 
  "field_name": "rounded_total", 
  "modified": "2015-06-09 14:34:20.147769", 
  "name": "Sales Invoice-rounded_total-hidden", 
  "property": "hidden", 
  "property_type": "Check", 
  "value": "0"
 }, 
 {
  "default_value": null, 
  "doc_type": "Sales Invoice", 
  "docstatus": 0, 
  "doctype": "Property Setter", 
  "doctype_or_field": "DocField", 
  "field_name": "rounded_total", 
  "modified": "2015-06-09 14:34:20.235069", 
  "name": "Sales Invoice-rounded_total-print_hide", 
  "property": "print_hide", 
  "property_type": "Check", 
  "value": "0"
 }, 
 {
  "default_value": null, 
  "doc_type": "Delivery Note", 
  "docstatus": 0, 
  "doctype": "Property Setter", 
  "doctype_or_field": "DocField", 
  "field_name": "base_rounded_total", 
  "modified": "2015-06-09 14:34:20.334822", 
  "name": "Delivery Note-base_rounded_total-hidden", 
  "property": "hidden", 
  "property_type": "Check", 
  "value": "0"
 }, 
 {
  "default_value": null, 
  "doc_type": "Delivery Note", 
  "docstatus": 0, 
  "doctype": "Property Setter", 
  "doctype_or_field": "DocField", 
  "field_name": "base_rounded_total", 
  "modified": "2015-06-09 14:34:20.417070", 
  "name": "Delivery Note-base_rounded_total-print_hide", 
  "property": "print_hide", 
  "property_type": "Check", 
  "value": "1"
 }, 
 {
  "default_value": null, 
  "doc_type": "Delivery Note", 
  "docstatus": 0, 
  "doctype": "Property Setter", 
  "doctype_or_field": "DocField", 
  "field_name": "rounded_total", 
  "modified": "2015-06-09 14:34:20.496864", 
  "name": "Delivery Note-rounded_total-hidden", 
  "property": "hidden", 
  "property_type": "Check", 
  "value": "0"
 }, 
 {
  "default_value": null, 
  "doc_type": "Delivery Note", 
  "docstatus": 0, 
  "doctype": "Property Setter", 
  "doctype_or_field": "DocField", 
  "field_name": "rounded_total", 
  "modified": "2015-06-09 14:34:20.572636", 
  "name": "Delivery Note-rounded_total-print_hide", 
  "property": "print_hide", 
  "property_type": "Check", 
  "value": "0"
 }, 
 {
  "default_value": null, 
  "doc_type": "Item", 
  "docstatus": 0, 
  "doctype": "Property Setter", 
  "doctype_or_field": "DocField", 
  "field_name": "naming_series", 
  "modified": "2015-06-09 14:34:22.078277", 
  "name": "Item-naming_series-reqd", 
  "property": "reqd", 
  "property_type": "Check", 
  "value": "0"
 }, 
 {
  "default_value": null, 
  "doc_type": "Item", 
  "docstatus": 0, 
  "doctype": "Property Setter", 
  "doctype_or_field": "DocField", 
  "field_name": "naming_series", 
  "modified": "2015-06-09 14:34:22.158942", 
  "name": "Item-naming_series-hidden", 
  "property": "hidden", 
  "property_type": "Check", 
  "value": "1"
 }, 
 {
  "default_value": null, 
  "doc_type": "Item", 
  "docstatus": 0, 
  "doctype": "Property Setter", 
  "doctype_or_field": "DocField", 
  "field_name": "item_code", 
  "modified": "2015-06-09 14:34:22.241025", 
  "name": "Item-item_code-hidden", 
  "property": "hidden", 
  "property_type": "Check", 
  "value": "0"
 }, 
 {
  "default_value": null, 
  "doc_type": "Item", 
  "docstatus": 0, 
  "doctype": "Property Setter", 
  "doctype_or_field": "DocField", 
  "field_name": "item_code", 
  "modified": "2015-06-09 14:34:22.331406", 
  "name": "Item-item_code-reqd", 
  "property": "reqd", 
  "property_type": "Check", 
  "value": "1"
 }, 
 {
  "default_value": null, 
  "doc_type": "Employee", 
  "docstatus": 0, 
  "doctype": "Property Setter", 
  "doctype_or_field": "DocField", 
  "field_name": "naming_series", 
  "modified": "2015-06-09 14:34:23.556475", 
  "name": "Employee-naming_series-hidden", 
  "property": "hidden", 
  "property_type": "Check", 
  "value": "0"
 }, 
 {
  "default_value": null, 
  "doc_type": "Employee", 
  "docstatus": 0, 
  "doctype": "Property Setter", 
  "doctype_or_field": "DocField", 
  "field_name": "naming_series", 
  "modified": "2015-06-09 14:34:23.623474", 
  "name": "Employee-naming_series-reqd", 
  "property": "reqd", 
  "property_type": "Check", 
  "value": "1"
 }, 
 {
  "default_value": null, 
  "doc_type": "Employee", 
  "docstatus": 0, 
  "doctype": "Property Setter", 
  "doctype_or_field": "DocField", 
  "field_name": "employee_number", 
  "modified": "2015-06-09 14:34:23.686695", 
  "name": "Employee-employee_number-reqd", 
  "property": "reqd", 
  "property_type": "Check", 
  "value": "0"
 }, 
 {
  "default_value": null, 
  "doc_type": "Employee", 
  "docstatus": 0, 
  "doctype": "Property Setter", 
  "doctype_or_field": "DocField", 
  "field_name": "employee_number", 
  "modified": "2015-06-09 14:34:23.747886", 
  "name": "Employee-employee_number-hidden", 
  "property": "hidden", 
  "property_type": "Check", 
  "value": "1"
 }, 
 {
  "default_value": null, 
  "doc_type": "Customer", 
  "docstatus": 0, 
  "doctype": "Property Setter", 
  "doctype_or_field": "DocField", 
  "field_name": "naming_series", 
  "modified": "2015-06-09 14:34:24.465687", 
  "name": "Customer-naming_series-reqd", 
  "property": "reqd", 
  "property_type": "Check", 
  "value": "0"
 }, 
 {
  "default_value": null, 
  "doc_type": "Customer", 
  "docstatus": 0, 
  "doctype": "Property Setter", 
  "doctype_or_field": "DocField", 
  "field_name": "naming_series", 
  "modified": "2015-06-09 14:34:24.522476", 
  "name": "Customer-naming_series-hidden", 
  "property": "hidden", 
  "property_type": "Check", 
  "value": "1"
 }, 
 {
  "default_value": null, 
  "doc_type": "Supplier", 
  "docstatus": 0, 
  "doctype": "Property Setter", 
  "doctype_or_field": "DocField", 
  "field_name": "naming_series", 
  "modified": "2015-06-09 14:34:24.923647", 
  "name": "Supplier-naming_series-reqd", 
  "property": "reqd", 
  "property_type": "Check", 
  "value": "0"
 }, 
 {
  "default_value": null, 
  "doc_type": "Supplier", 
  "docstatus": 0, 
  "doctype": "Property Setter", 
  "doctype_or_field": "DocField", 
  "field_name": "naming_series", 
  "modified": "2015-06-09 14:34:24.956656", 
  "name": "Supplier-naming_series-hidden", 
  "property": "hidden", 
  "property_type": "Check", 
  "value": "1"
 }, 
 {
  "default_value": null, 
  "doc_type": "Sales Invoice", 
  "docstatus": 0, 
  "doctype": "Property Setter", 
  "doctype_or_field": "DocField", 
  "field_name": "paypal_amount", 
  "modified": "2015-06-09 15:27:28.175339", 
  "name": "Sales Invoice-paypal_amount-previous_field", 
  "property": "previous_field", 
  "property_type": "Data", 
  "value": "outstanding_amount"
 }
]